{"success": true, "data": [{"user": {"name": "p4st1s", "id": 2123}, "date": "2024-08-30T23:51:46.473571+00:00", "type": "correct", "challenge_id": 43, "challenge": {"name": "Geometry Dash 2.1", "value": 50, "id": 43, "category": "forensics"}, "team": {"name": "Phreaks 2600", "id": 1054}, "id": 5176}, {"user": {"name": "p4st1s", "id": 2123}, "date": "2024-08-30T23:43:31.284012+00:00", "type": "correct", "challenge_id": 42, "challenge": {"name": "Social Distancing", "value": 50, "id": 42, "category": "forensics"}, "team": {"name": "Phreaks 2600", "id": 1054}, "id": 5146}, {"user": {"name": "p4st1s", "id": 2123}, "date": "2024-08-30T22:49:10.786822+00:00", "type": "correct", "challenge_id": 37, "challenge": {"name": "key", "value": 50, "id": 37, "category": "beginner"}, "team": {"name": "Phreaks 2600", "id": 1054}, "id": 4874}, {"user": {"name": "p4st1s", "id": 2123}, "date": "2024-08-30T22:16:09.705603+00:00", "type": "correct", "challenge_id": 41, "challenge": {"name": "Baby Pybash", "value": 50, "id": 41, "category": "beginner"}, "team": {"name": "Phreaks 2600", "id": 1054}, "id": 4665}, {"user": {"name": "p4st1s", "id": 2123}, "date": "2024-08-30T19:40:00.375582+00:00", "type": "correct", "challenge_id": 34, "challenge": {"name": "encryptor", "value": 50, "id": 34, "category": "beginner"}, "team": {"name": "Phreaks 2600", "id": 1054}, "id": 3313}], "meta": {"count": 5}}
