{"success": true, "data": [{"user": {"name": "nsdib", "id": 1907}, "date": "2024-09-01T01:48:32.002476+00:00", "type": "correct", "challenge_id": 55, "challenge": {"name": "ezcoppersmith", "value": 50, "id": 55, "category": "crypto"}, "team": {"name": "FPUSEC", "id": 863}, "id": 11282}, {"user": {"name": "nsdib", "id": 1907}, "date": "2024-08-30T17:35:45.416504+00:00", "type": "correct", "challenge_id": 22, "challenge": {"name": "Sanity Check", "value": 50, "id": 22, "category": "misc"}, "team": {"name": "FPUSEC", "id": 863}, "id": 777}, {"user": {"name": "nsdib", "id": 1907}, "date": "2024-08-30T17:34:40.549837+00:00", "type": "correct", "challenge_id": 37, "challenge": {"name": "key", "value": 50, "id": 37, "category": "beginner"}, "team": {"name": "FPUSEC", "id": 863}, "id": 742}], "meta": {"count": 3}}
