{"success": true, "data": [{"user": {"name": "ahegao king", "id": 2106}, "date": "2024-09-01T13:41:29.494303+00:00", "type": "correct", "challenge_id": 57, "challenge": {"name": "sole", "value": 316, "id": 57, "category": "rev"}, "team": {"name": "balchal", "id": 1058}, "id": 12525}, {"user": {"name": "ahegao king", "id": 2106}, "date": "2024-08-31T13:08:45.915202+00:00", "type": "correct", "challenge_id": 14, "challenge": {"name": "login", "value": 383, "id": 14, "category": "rev"}, "team": {"name": "balchal", "id": 1058}, "id": 9000}, {"user": {"name": "ahegao king", "id": 2106}, "date": "2024-08-30T23:22:34.670464+00:00", "type": "correct", "challenge_id": 15, "challenge": {"name": "snake", "value": 50, "id": 15, "category": "rev"}, "team": {"name": "balchal", "id": 1058}, "id": 5063}, {"user": {"name": "ahegao king", "id": 2106}, "date": "2024-08-30T20:10:52.093697+00:00", "type": "correct", "challenge_id": 34, "challenge": {"name": "encryptor", "value": 50, "id": 34, "category": "beginner"}, "team": {"name": "balchal", "id": 1058}, "id": 3621}, {"user": {"name": "ahegao king", "id": 2106}, "date": "2024-08-30T20:01:45.702143+00:00", "type": "correct", "challenge_id": 37, "challenge": {"name": "key", "value": 50, "id": 37, "category": "beginner"}, "team": {"name": "balchal", "id": 1058}, "id": 3481}], "meta": {"count": 5}}
