{"success": true, "data": [{"user": {"name": "thejuggler35", "id": 3104}, "date": "2024-09-01T07:54:24.913832+00:00", "type": "correct", "challenge_id": 76, "challenge": {"name": "Feedback", "value": 1, "id": 76, "category": "misc"}, "team": {"name": "thejuggler35", "id": 1616}, "id": 11898}, {"user": {"name": "thejuggler35", "id": 3104}, "date": "2024-09-01T07:39:34.981037+00:00", "type": "correct", "challenge_id": 22, "challenge": {"name": "Sanity Check", "value": 50, "id": 22, "category": "misc"}, "team": {"name": "thejuggler35", "id": 1616}, "id": 11857}], "meta": {"count": 2}}
