{"success": true, "data": [{"user": {"name": "asdfasdf12341234", "id": 111}, "date": "2024-08-30T23:05:40.199734+00:00", "type": "correct", "challenge_id": 55, "challenge": {"name": "ezcoppersmith", "value": 50, "id": 55, "category": "crypto"}, "team": {"name": "asdfasdf12341234", "id": 51}, "id": 4972}, {"user": {"name": "asdfasdf12341234", "id": 111}, "date": "2024-08-30T23:04:17.546632+00:00", "type": "correct", "challenge_id": 28, "challenge": {"name": "\ud83c\udd70\ufe0f \ud83e\uddb5 \ud83c\udf31", "value": 50, "id": 28, "category": "sponsor"}, "team": {"name": "asdfasdf12341234", "id": 51}, "id": 4960}, {"user": {"name": "asdfasdf12341234", "id": 111}, "date": "2024-08-30T22:39:11.389149+00:00", "type": "correct", "challenge_id": 22, "challenge": {"name": "Sanity Check", "value": 50, "id": 22, "category": "misc"}, "team": {"name": "asdfasdf12341234", "id": 51}, "id": 4824}, {"user": {"name": "asdfasdf12341234", "id": 111}, "date": "2024-08-30T22:24:19.138109+00:00", "type": "correct", "challenge_id": 34, "challenge": {"name": "encryptor", "value": 50, "id": 34, "category": "beginner"}, "team": {"name": "asdfasdf12341234", "id": 51}, "id": 4736}, {"user": {"name": "asdfasdf12341234", "id": 111}, "date": "2024-08-30T21:58:32.800571+00:00", "type": "correct", "challenge_id": 37, "challenge": {"name": "key", "value": 50, "id": 37, "category": "beginner"}, "team": {"name": "asdfasdf12341234", "id": 51}, "id": 4557}], "meta": {"count": 5}}
